<?xml version="1.0" standalone="yes"?>
<resources>
  <resource culture="es-es" name="Agencia" value="Agencia"></resource>
  <resource culture="es-es" name="Clave" value="Clave"></resource>
  <resource culture="es-es" name="Clave_de_Municipio" value="Clave de Municipio"></resource>
  <resource culture="es-es" name="Descripcion" value="Descripción"></resource>
  <resource culture="es-es" name="Activa" value="Activa"></resource>
  <resource culture="es-es" name="ClaveID" value="ClaveID"></resource>

<resource culture="es-es" name="TabDatos_Generales" value="Datos Generales"></resource>

</resources>
