<?xml version="1.0" standalone="yes"?>
<resources>
  <resource culture="en-us" name="Delegacion" value="Delegación"></resource>
  <resource culture="en-US" name="Clave" value="Clave"></resource>
  <resource culture="en-US" name="Descripcion" value="Descripción"></resource>
  <resource culture="en-US" name="Zona" value="Zona"></resource>
  <resource culture="en-US" name="Clave_Expediente" value="Clave Expediente"></resource>
  <resource culture="en-US" name="Direccion" value="Dirección"></resource>
  <resource culture="en-US" name="Consecutivo_MPO" value="Consecutivo MPO"></resource>
  <resource culture="en-US" name="Consecutivo_MPI" value="Consecutivo MPI"></resource>
  <resource culture="en-US" name="Distrito" value="Distrito"></resource>
  <resource culture="en-US" name="Abreviacion_Delegacion" value="Abreviación Delegación"></resource>

<resource culture="en-US" name="TabDatos_Generales" value="Datos Generales"></resource>

</resources>
